gahto/gahto.py
gahto/py.typed
gahto-0.0.1.dist-info/LICENSE
gahto-0.0.1.dist-info/METADATA
gahto-0.0.1.dist-info/WHEEL
gahto-0.0.1.dist-info/top_level.txt
gahto-0.0.1.dist-info/RECORD
