Metadata-Version: 2.2
Name: gahto
Version: 0.0.1
Summary: GAHTO is a small Python module for creating GNUCash Account Hierarchy Template Objects natively in python, and eventually exporting them in XML as .gnucash-xea files.
Author-email: 7heo <7heo@users.noreply.github.com>
License: BSD-3-Clause
Project-URL: Homepage, https://github.com/7heo/GAHTO
Project-URL: Issues, https://github.com/7heo/GAHTO/issues
Classifier: Programming Language :: Python :: 3
Classifier: Operating System :: OS Independent
Requires-Python: >=3.9
License-File: LICENSE
Requires-Dist: pint
Requires-Dist: iso-4217
